snakeboost/__init__.py
snakeboost/bash/__init__.py
snakeboost/bash/abstract.py
snakeboost/bash/awk.py
snakeboost/bash/cmd.py
snakeboost/bash/globals.py
snakeboost/bash/statement.py
snakeboost/bash/utils.py
snakeboost/boost.py
snakeboost/datalad.py
snakeboost/pipenv.py
snakeboost/script.py
snakeboost/tar.py
snakeboost/utils.py
snakeboost/xvfb.py
snakeboost-0.3.0.dist-info/WHEEL
snakeboost-0.3.0.dist-info/METADATA
snakeboost-0.3.0.dist-info/RECORD
