Metadata-Version: 2.1
Name: snakeboost
Version: 0.3.0
Summary: Utility functions to turbocharge your snakemake workflows. Virtualenvs, tarfiles, and more.
License: MIT
Keywords: snakemake,workflow,data science,utility,helpers
Author: Peter Van Dyken
Author-email: pvandyk2@uwo.ca
Requires-Python: >=3.7,<3.11
Classifier: Development Status :: 3 - Alpha
Classifier: Environment :: Console
Classifier: Intended Audience :: Science/Research
Classifier: License :: OSI Approved :: MIT License
Classifier: Natural Language :: English
Classifier: Operating System :: POSIX :: Linux
Classifier: Programming Language :: Python :: 3
Classifier: Programming Language :: Python :: 3.10
Classifier: Programming Language :: Python :: 3.7
Classifier: Programming Language :: Python :: 3.8
Classifier: Programming Language :: Python :: 3.9
Classifier: Topic :: Utilities
Classifier: Typing :: Typed
Requires-Dist: Pygments (>=2.10.0,<3.0.0)
Requires-Dist: attrs (>=21.2.0,<22.0.0)
Requires-Dist: colorama (>=0.4.4,<0.5.0)
Requires-Dist: more-itertools (>=8.8.0,<9.0.0)
